anthropicautodocstrings/__init__.py
anthropicautodocstrings/main.py
anthropicautodocstrings-0.0.8.dist-info/METADATA
anthropicautodocstrings-0.0.8.dist-info/WHEEL
anthropicautodocstrings-0.0.8.dist-info/entry_points.txt
anthropicautodocstrings-0.0.8.dist-info/licenses/LICENSE
anthropicautodocstrings-0.0.8.dist-info/RECORD
