Metadata-Version: 2.4
Name: anthropicautodocstrings
Version: 0.0.8
Summary: Anthropic Auto Docstrings Generator
License: GPL-3.0-or-later
License-File: LICENSE
Author: Jordan McLaughlin
Author-email: cantoo@duck.com
Maintainer: Jordan McLaughlin
Maintainer-email: cantoo@duck.com
Requires-Python: >=3.10,<4.0
Classifier: License :: OSI Approved :: GNU General Public License v3 or later (GPLv3+)
Classifier: Programming Language :: Python :: 3
Classifier: Programming Language :: Python :: 3.10
Classifier: Programming Language :: Python :: 3.11
Classifier: Programming Language :: Python :: 3.12
Classifier: Programming Language :: Python :: 3.13
Classifier: Programming Language :: Python :: 3.14
Requires-Dist: anthropic (>=0.72.0,<0.73.0)
Requires-Dist: astor (>=0.8.1,<0.9.0)
Requires-Dist: black (>=25.9.0,<26.0.0)
Requires-Dist: certifi (>=2025.10.5,<2026.0.0)
Requires-Dist: typer (>=0.20.0,<0.21.0)
Project-URL: Repository, https://github.com/JordanM575/anthropicautodocstrings
